math_t/__init__.py
math_t/demo1.py
math_t/demo2.py
math_t-1.0.dist-info/METADATA
math_t-1.0.dist-info/WHEEL
math_t-1.0.dist-info/top_level.txt
math_t-1.0.dist-info/RECORD
