Metadata-Version: 2.1
Name: math-t
Version: 1.0
Summary: 这是一个发布模块，测试
Author: linan
Author-email: 365763491@qq.com
